Products.PlonePAS-8.0.5-py3.13-nspkg.pth
Products/PlonePAS/__init__.py
Products/PlonePAS/config.py
Products/PlonePAS/configure.zcml
Products/PlonePAS/events.py
Products/PlonePAS/exportimport.zcml
Products/PlonePAS/pas.py
Products/PlonePAS/patch.py
Products/PlonePAS/permissions.py
Products/PlonePAS/profiles.zcml
Products/PlonePAS/setuphandlers.py
Products/PlonePAS/sheet.py
Products/PlonePAS/testing.py
Products/PlonePAS/tool.gif
Products/PlonePAS/upgrades.py
Products/PlonePAS/utils.py
Products/PlonePAS/browser/__init__.py
Products/PlonePAS/browser/configure.zcml
Products/PlonePAS/browser/info.py
Products/PlonePAS/browser/member.py
Products/PlonePAS/browser/search.py
Products/PlonePAS/interfaces/__init__.py
Products/PlonePAS/interfaces/browser.py
Products/PlonePAS/interfaces/capabilities.py
Products/PlonePAS/interfaces/events.py
Products/PlonePAS/interfaces/group.py
Products/PlonePAS/interfaces/memberdata.py
Products/PlonePAS/interfaces/membership.py
Products/PlonePAS/interfaces/plugins.py
Products/PlonePAS/interfaces/propertysheets.py
Products/PlonePAS/plugins/__init__.py
Products/PlonePAS/plugins/autogroup.py
Products/PlonePAS/plugins/cookie_handler.py
Products/PlonePAS/plugins/crumbler.py
Products/PlonePAS/plugins/group.py
Products/PlonePAS/plugins/local_role.py
Products/PlonePAS/plugins/passwordpolicy.py
Products/PlonePAS/plugins/property.py
Products/PlonePAS/plugins/role.py
Products/PlonePAS/plugins/ufactory.py
Products/PlonePAS/plugins/user.py
Products/PlonePAS/profiles/default/metadata.xml
Products/PlonePAS/profiles/default/plone-pas.txt
Products/PlonePAS/profiles/root-cookie/metadata.xml
Products/PlonePAS/profiles/root-cookie/plone-pas-zope-root-cookie.txt
Products/PlonePAS/tests/__init__.py
Products/PlonePAS/tests/cookie_auth.rst
Products/PlonePAS/tests/dummy.py
Products/PlonePAS/tests/test_basic_ops.py
Products/PlonePAS/tests/test_doctests.py
Products/PlonePAS/tests/test_groupdatatool.py
Products/PlonePAS/tests/test_groupstool.py
Products.PlonePAS-8.0.5.dist-info/METADATA
Products.PlonePAS-8.0.5.dist-info/WHEEL
Products.PlonePAS-8.0.5.dist-info/namespace_packages.txt
Products.PlonePAS-8.0.5.dist-info/top_level.txt
Products.PlonePAS-8.0.5.dist-info/RECORD
