Metadata-Version: 2.1
Name: Products.PlonePAS
Version: 8.0.5
Summary: PlonePAS modifies the PluggableAuthService for use by Plone.
Home-page: https://github.com/plone/Products.PlonePAS
Author: Kapil Thangavelu, Wichert Akkerman
Author-email: plone-developers@lists.sourceforge.net
License: ZPL
Keywords: Zope CMF Plone PAS authentication
Classifier: Development Status :: 5 - Production/Stable
Classifier: Framework :: Plone
Classifier: Framework :: Plone :: 6.0
Classifier: Framework :: Plone :: Core
Classifier: Framework :: Zope
Classifier: Framework :: Zope :: 5
Classifier: License :: OSI Approved :: Zope Public License
Classifier: Programming Language :: Python
Classifier: Programming Language :: Python :: 3.8
Classifier: Programming Language :: Python :: 3.9
Classifier: Programming Language :: Python :: 3.10
Classifier: Programming Language :: Python :: 3.11
Requires-Python: >=3.8
Requires-Dist: Pillow
Requires-Dist: plone.base
Requires-Dist: plone.i18n
Requires-Dist: plone.memoize
Requires-Dist: plone.protect>=2.0.3
Requires-Dist: plone.registry
Requires-Dist: plone.session
Requires-Dist: Products.BTreeFolder2
Requires-Dist: Products.GenericSetup
Requires-Dist: Products.PluggableAuthService>=2.0
Requires-Dist: setuptools
Requires-Dist: Zope
Provides-Extra: test
Requires-Dist: plone.app.testing; extra == "test"
Requires-Dist: plone.app.contenttypes[test]; extra == "test"
Requires-Dist: plone.testing; extra == "test"
Requires-Dist: Products.PluginRegistry; extra == "test"
